mlbot/__init__.py
mlbot/handlers.py
mlbot/mlflow_handlers.py
mlbot/utils.py
mlbot/static/handlers.js
mlbot/static/main.js
mlbot-0.0.1a1.dev15.data/data/etc/jupyter/jupyter_notebook_config.d/mlbot.json
mlbot-0.0.1a1.dev15.data/data/etc/jupyter/nbconfig/notebook.d/mlbot.json
mlbot-0.0.1a1.dev15.data/data/share/jupyter/nbextensions/mlbot/handlers.js
mlbot-0.0.1a1.dev15.data/data/share/jupyter/nbextensions/mlbot/main.js
mlbot-0.0.1a1.dev15.dist-info/LICENSE
mlbot-0.0.1a1.dev15.dist-info/METADATA
mlbot-0.0.1a1.dev15.dist-info/WHEEL
mlbot-0.0.1a1.dev15.dist-info/top_level.txt
mlbot-0.0.1a1.dev15.dist-info/RECORD
